[
    {
       "codigo":"1",
       "origen":"Barranquilla",
       "direccion":"calle #20 23-55",
       "fecha":"17/12/2021",
       "hora":"8:00",
       "detalles":"Mercancía frágil",
       "destino":"Cali",
       "estado":"Entregado"
      
    },
    {
        "codigo":"2",
       "origen":"Barranquilla",
       "direccion":"calle #20 23-55",
       "fecha":"17/12/2021",
       "hora":"8:00",
       "detalles":"Mercancía frágil",
       "destino":"Cali",
       "estado":"Entregado"
    },
    {
        "codigo":"3",
       "origen":"Cartagena",
       "direccion":"calle #20 23-55",
       "fecha":"17/12/2021",
       "hora":"8:00",
       "detalles":"Mercancía frágil",
       "destino":"Medellín",
       "estado":"Entregado"
    },
    {
        "codigo":"4",
        "origen":"Barranquilla",
        "direccion":"calle #20 23-55",
        "fecha":"17/12/2021",
        "hora":"8:00",
        "detalles":"Mercancía frágil",
        "destino":"Bogotá",
        "estado":"Entregado"
    },
    {
        "codigo":"5",
        "origen":"Barranquilla",
        "direccion":"calle #20 23-55",
        "fecha":"17/12/2021",
        "hora":"8:00",
        "detalles":"Mercancía frágil",
        "destino":"Sincelejo",
        "estado":"Recogido"
    },
    {
        "codigo":"6",
        "origen":"Barranquilla",
        "direccion":"calle #20 23-55",
        "fecha":"17/12/2021",
        "hora":"8:00",
        "detalles":"Mercancía frágil",
        "destino":"Montería",
        "estado":"Recogido"
    }
 ]